mock_idp-0.5.1.data/scripts/mock-idp
mockidp/__init__.py
mockidp/__version__.py
mockidp/app.py
mockidp/main.py
mockidp/routes.py
mockidp/core/__init__.py
mockidp/core/auth.py
mockidp/core/config.py
mockidp/core/session.py
mockidp/keys/cert.pem
mockidp/keys/key.pem
mockidp/resources/default_config.yaml
mockidp/resources/css/login.css
mockidp/resources/img/loading.gif
mockidp/saml/__init__.py
mockidp/saml/request.py
mockidp/saml/response.py
mockidp/saml/routes.py
mockidp/templates/auth_response.html
mockidp/templates/login.html
mockidp/templates/saml_response.xml
mockidp/templates/saml/logout.html
mockidp/templates/saml/logout_response.xml
tests/__init__.py
tests/test_auth.py
tests/test_config.py
tests/test_session.py
tests/saml/__init__.py
tests/saml/test_request.py
tests/saml/test_response.py
mock_idp-0.5.1.dist-info/LICENSE
mock_idp-0.5.1.dist-info/METADATA
mock_idp-0.5.1.dist-info/WHEEL
mock_idp-0.5.1.dist-info/top_level.txt
mock_idp-0.5.1.dist-info/RECORD
