Metadata-Version: 2.1
Name: mock-idp
Version: 0.5.1
Summary: Mock SAML 2.0 Identity Provider
Author: =?utf-8?q?Bj=C3=B6rn_Skoglund?=
Author-email: bjorn.skoglund@icloud.com
License: MIT
Classifier: Development Status :: 4 - Beta
Classifier: Intended Audience :: Developers
Classifier: Topic :: Software Development
Classifier: License :: OSI Approved :: MIT License
Classifier: Programming Language :: Python :: 3.7
License-File: LICENSE
Requires-Dist: flask
Requires-Dist: lxml
Requires-Dist: PyYAML
Requires-Dist: flask-script
Requires-Dist: signxml
Requires-Dist: nose
